perceptron/__init__.py
perceptron/perceptron.py
Perceptron_PyPi_manan_bedi2908-0.0.2.dist-info/LICENSE
Perceptron_PyPi_manan_bedi2908-0.0.2.dist-info/METADATA
Perceptron_PyPi_manan_bedi2908-0.0.2.dist-info/WHEEL
Perceptron_PyPi_manan_bedi2908-0.0.2.dist-info/top_level.txt
Perceptron_PyPi_manan_bedi2908-0.0.2.dist-info/RECORD
